Codigos/7_shift_reg_1ra_ aprox/fuentes/shift_reg.vhd
library IEEE;
use IEEE.std_logic_1164.all;

entity shift_reg is
	generic (
		N: natural := 4
	);
	port (
		clk: in std_logic;
		rst: in std_logic;
		ena: in std_logic;
		ent: in std_logic;
		sal: out std_logic_vector( 3 downto 0)
	);
end;

architecture shift_reg_arq of shift_reg is
	
	signal sal_aux: std_logic_vector(3 downto 0):= "0000";
	
begin

	shift_p: process(clk)
		begin
		if rst='1' then
			sal_aux <= "0000";
			sal <= sal_aux;
		else
			if rising_edge(clk) then
				if sal_aux="0000" then
					sal_aux<="0001";
					sal <= sal_aux;
					elsif sal_aux="0001" then
						sal_aux<="0010";
						sal <= sal_aux;
					elsif sal_aux="0010" then
						sal_aux<="0100";
						sal <= sal_aux;
					elsif sal_aux="0100" then
						sal_aux<="1000";
						sal <= sal_aux;
					elsif sal_aux="1000" then
						sal_aux<="0000";
						sal <= sal_aux;
				else
					sal_aux<="1111";
					sal <= sal_aux;
				end if;	
			end if;
		end if;	
	end process;

end;

Codigos/7_shift_reg_1ra_ aprox/fuentes/shift_reg_tb.vhd
library IEEE;
use IEEE.std_logic_1164.all;

entity shift_reg_tb is
end;

architecture shift_reg_tb_arq of shift_reg_tb is
	component shift_reg is
		generic (
			N: natural := 4
		);
		port (
			clk: in std_logic;
			rst: in std_logic;
			ena: in std_logic;
			ent: in std_logic;
			sal: out std_logic_vector(3 downto 0)
		);
	end component;

	signal clk_tb: std_logic := '0';
	signal rst_tb: std_logic := '0';
	signal ena_tb: std_logic := '0';
	signal ent_tb: std_logic := '0';
	signal sal_tb: std_logic_vector(3 downto 0);
	
begin

	clk_tb <= not clk_tb after 20 ns;
	--clk_tb <= '0', '1' after 20 ns,'0' after 40 ns,'1' after 60 ns,'0' after 80 ns,'1' after 100 ns;
	rst_tb <= '1', '0' after 30 ns;
	ena_tb <= '0', '1' after 50 ns;
	ent_tb <= '1', '0' after 70 ns;
	

	--DUT: entity work.ffd
	--DUT: entity work.shift_reg
	DUT:shift_reg
		port map(
			clk => 	clk_tb,
			rst => 	rst_tb,
			ena => 	ena_tb,
			ent => 	ent_tb,
			sal =>	sal_tb
		);
end;

Codigos/7_shift_reg_1ra_ aprox/simulacion/shift_reg_tb.vcd
$date
  Mon Apr  5 08:40:00 2021
$end
$version
  GHDL v0
$end
$timescale
  1 fs
$end
$scope module standard $end
$upscope $end
$scope module std_logic_1164 $end
$upscope $end
$scope module shift_reg_tb $end
$var reg 1 ! clk_tb $end
$var reg 1 " rst_tb $end
$var reg 1 # ena_tb $end
$var reg 1 $ ent_tb $end
$var reg 4 % sal_tb[3:0] $end
$scope module dut $end
$var reg 1 & clk $end
$var reg 1 ' rst $end
$var reg 1 ( ena $end
$var reg 1 ) ent $end
$var reg 4 * sal[3:0] $end
$var reg 4 + sal_aux[3:0] $end
$upscope $end
$upscope $end
$enddefinitions $end
#0
0!
1"
0#
1$
bUUUU %
0&
1'
0(
1)
bUUUU *
b0000 +
#20000000
1!
b0000 %
1&
b0000 *
#30000000
0"
0'
#40000000
0!
0&
#50000000
1#
1(
#60000000
1!
1&
b0001 +
#70000000
0$
0)
#80000000
0!
0&
#100000000
1!
b0001 %
1&
b0001 *
b0010 +
#120000000
0!
0&
#140000000
1!
b0010 %
1&
b0010 *
b0100 +
#160000000
0!
0&
#180000000
1!
b0100 %
1&
b0100 *
b1000 +
#200000000
0!
0&
#220000000
1!
b1000 %
1&
b1000 *
b0000 +
#240000000
0!
0&
#260000000
1!
b0000 %
1&
b0000 *
b0001 +
#280000000
0!
0&
#300000000
1!
b0001 %
1&
b0001 *
b0010 +
#320000000
0!
0&
#340000000
1!
b0010 %
1&
b0010 *
b0100 +
#360000000
0!
0&
#380000000
1!
b0100 %
1&
b0100 *
b1000 +
#400000000
0!
0&
#420000000
1!
b1000 %
1&
b1000 *
b0000 +
#440000000
0!
0&
#460000000
1!
b0000 %
1&
b0000 *
b0001 +
#480000000
0!
0&
#500000000
1!
b0001 %
1&
b0001 *
b0010 +
