Codigos/15_contador_BCD_1digito/fuentes/contador_bcd.vhd
library IEEE;
use IEEE.std_logic_1164.all;
use IEEE.numeric_std.all;

entity contador_bcd is
	generic (
		N: natural := 4
	);
	port(
		clk: 	in std_logic;
		rst: 	in std_logic;
		ena: 	in std_logic;
		cy: 	out std_logic;
		Q: 		out std_logic_vector(N-1 downto 0)
	);
end;

architecture contador_bcd_arq of contador_bcd is

	--Inicializo salidas
	signal Q_aux: std_logic_vector(N-1 downto 0):=std_logic_vector(to_unsigned(0,N));
	
	begin
    proceso_contador: process (ena, clk,rst) is
    	variable count: integer range 0 to 512:=0;
		begin
        if rst = '1' then
            Q_aux <= std_logic_vector(to_unsigned(0,N));
            count:=0;
            cy <='0';
			elsif rising_edge(clk) and ena='1' then
				count:= to_integer(unsigned(Q_aux));
				count:= count+1;
				if count=10 then
				    Q_aux <= std_logic_vector(to_unsigned(0,N));
					count:=0;
					cy <= '1';
					else
						Q_aux <= std_logic_vector(to_unsigned(count,N));
						cy <= '0';
				end if;
		end if;
    end process  proceso_contador;
    Q <= Q_aux;
end;

Codigos/15_contador_BCD_1digito/fuentes/contador_bcd_tb.vhd
library IEEE;
use IEEE.std_logic_1164.all;

entity contador_bcd_tb is
		generic (
			N: natural := 4
		);
end;

architecture contador_bcd_tb_arq of contador_bcd_tb is

	component contador_bcd is
		generic (
			N: natural := 4
		);
		port(
			clk: 	in std_logic;
			rst: 	in std_logic;
			ena: 	in std_logic;
			cy: 	out std_logic;
			Q: 		out std_logic_vector(N-1 downto 0)
		);
	end component;

	signal clk_tb: std_logic := '0';
	signal rst_tb: std_logic := '0';
	signal ena_tb: std_logic := '0';
	signal cy_tb: std_logic := '0';
	signal Q_tb: std_logic_vector(N-1 downto 0);
	
begin
	clk_tb <= not clk_tb after 10 ns;
	ena_tb <= '0', '1' after 50 ns,'0' after 450 ns,'1' after 500 ns;
	rst_tb <= '1', '0' after 30 ns, '1' after 400 ns, '0' after 430 ns;

	DUT: contador_bcd
		port map(
			clk => 	clk_tb,
			rst => 	rst_tb,
			ena => 	ena_tb,
			cy => 	cy_tb,
			Q =>	Q_tb
		);
end;

Codigos/15_contador_BCD_1digito/simulacion/contador_bcd_tb.vcd
$date
  Tue Apr  6 13:52:54 2021
$end
$version
  GHDL v0
$end
$timescale
  1 fs
$end
$scope module standard $end
$upscope $end
$scope module std_logic_1164 $end
$upscope $end
$scope module numeric_std $end
$upscope $end
$scope module contador_bcd_tb $end
$var reg 1 ! clk_tb $end
$var reg 1 " rst_tb $end
$var reg 1 # ena_tb $end
$var reg 1 $ cy_tb $end
$var reg 4 % q_tb[3:0] $end
$scope module dut $end
$var reg 1 & clk $end
$var reg 1 ' rst $end
$var reg 1 ( ena $end
$var reg 1 ) cy $end
$var reg 4 * q[3:0] $end
$var reg 4 + q_aux[3:0] $end
$upscope $end
$upscope $end
$enddefinitions $end
#0
0!
1"
0#
0$
b0000 %
0&
1'
0(
0)
b0000 *
b0000 +
#10000000
1!
1&
#20000000
0!
0&
#30000000
1!
0"
1&
0'
#40000000
0!
0&
#50000000
1!
1#
b0001 %
1&
1(
b0001 *
b0001 +
#60000000
0!
0&
#70000000
1!
b0010 %
1&
b0010 *
b0010 +
#80000000
0!
0&
#90000000
1!
b0011 %
1&
b0011 *
b0011 +
#100000000
0!
0&
#110000000
1!
b0100 %
1&
b0100 *
b0100 +
#120000000
0!
0&
#130000000
1!
b0101 %
1&
b0101 *
b0101 +
#140000000
0!
0&
#150000000
1!
b0110 %
1&
b0110 *
b0110 +
#160000000
0!
0&
#170000000
1!
b0111 %
1&
b0111 *
b0111 +
#180000000
0!
0&
#190000000
1!
b1000 %
1&
b1000 *
b1000 +
#200000000
0!
0&
#210000000
1!
b1001 %
1&
b1001 *
b1001 +
#220000000
0!
0&
#230000000
1!
1$
b0000 %
1&
1)
b0000 *
b0000 +
#240000000
0!
0&
#250000000
1!
0$
b0001 %
1&
0)
b0001 *
b0001 +
#260000000
0!
0&
#270000000
1!
b0010 %
1&
b0010 *
b0010 +
#280000000
0!
0&
#290000000
1!
b0011 %
1&
b0011 *
b0011 +
#300000000
0!
0&
#310000000
1!
b0100 %
1&
b0100 *
b0100 +
#320000000
0!
0&
#330000000
1!
b0101 %
1&
b0101 *
b0101 +
#340000000
0!
0&
#350000000
1!
b0110 %
1&
b0110 *
b0110 +
#360000000
0!
0&
#370000000
1!
b0111 %
1&
b0111 *
b0111 +
#380000000
0!
0&
#390000000
1!
b1000 %
1&
b1000 *
b1000 +
#400000000
0!
1"
b0000 %
0&
1'
b0000 *
b0000 +
#410000000
1!
1&
#420000000
0!
0&
#430000000
1!
0"
b0001 %
1&
0'
b0001 *
b0001 +
#440000000
0!
0&
#450000000
1!
0#
1&
0(
#460000000
0!
0&
#470000000
1!
1&
#480000000
0!
0&
#490000000
1!
1&
#500000000
0!
1#
0&
1(
#510000000
1!
b0010 %
1&
b0010 *
b0010 +
#520000000
0!
0&
#530000000
1!
b0011 %
1&
b0011 *
b0011 +
#540000000
0!
0&
#550000000
1!
b0100 %
1&
b0100 *
b0100 +
#560000000
0!
0&
#570000000
1!
b0101 %
1&
b0101 *
b0101 +
#580000000
0!
0&
#590000000
1!
b0110 %
1&
b0110 *
b0110 +
#600000000
0!
0&
#610000000
1!
b0111 %
1&
b0111 *
b0111 +
#620000000
0!
0&
#630000000
1!
b1000 %
1&
b1000 *
b1000 +
#640000000
0!
0&
#650000000
1!
b1001 %
1&
b1001 *
b1001 +
#660000000
0!
0&
#670000000
1!
1$
b0000 %
1&
1)
b0000 *
b0000 +
#680000000
0!
0&
#690000000
1!
0$
b0001 %
1&
0)
b0001 *
b0001 +
#700000000
0!
0&
#710000000
1!
b0010 %
1&
b0010 *
b0010 +
#720000000
0!
0&
#730000000
1!
b0011 %
1&
b0011 *
b0011 +
#740000000
0!
0&
#750000000
1!
b0100 %
1&
b0100 *
b0100 +
#760000000
0!
0&
#770000000
1!
b0101 %
1&
b0101 *
b0101 +
#780000000
0!
0&
#790000000
1!
b0110 %
1&
b0110 *
b0110 +
#800000000
0!
0&
#810000000
1!
b0111 %
1&
b0111 *
b0111 +
#820000000
0!
0&
#830000000
1!
b1000 %
1&
b1000 *
b1000 +
#840000000
0!
0&
#850000000
1!
b1001 %
1&
b1001 *
b1001 +
#860000000
0!
0&
#870000000
1!
1$
b0000 %
1&
1)
b0000 *
b0000 +
#880000000
0!
0&
#890000000
1!
0$
b0001 %
1&
0)
b0001 *
b0001 +
#900000000
0!
0&
#910000000
1!
b0010 %
1&
b0010 *
b0010 +
#920000000
0!
0&
#930000000
1!
b0011 %
1&
b0011 *
b0011 +
#940000000
0!
0&
#950000000
1!
b0100 %
1&
b0100 *
b0100 +
#960000000
0!
0&
#970000000
1!
b0101 %
1&
b0101 *
b0101 +
#980000000
0!
0&
#990000000
1!
b0110 %
1&
b0110 *
b0110 +
