Codigos/contador_Nfft/fuentes/fft.vhd
library IEEE;
use IEEE.std_logic_1164.all;

entity fft is
	port(
		clk: 	in std_logic;
		rst: 	in std_logic;
		ena: 	in std_logic;
		T:	in std_logic;
		Q:	out std_logic
	);
	end fft;

architecture fft_arq of fft is
signal q_aux: std_logic;
begin
	process(clk,rst)
		begin
		if rst='1' then
			Q<='0';
		elsif falling_edge(clk) then	
			if ena='1' and T='1' then	
				if  q_aux='1' then
				    q_aux<= '0';
					Q <= '0';
				else
				    q_aux<='1';
					Q <= '1';
				end if;
			end if;
		end if;
	end process;
Q <= q_aux;
end fft_arq;

Codigos/fft/fuentes/fft_tb.vhd
library IEEE;
use IEEE.std_logic_1164.all;

entity fft_tb is
end;

architecture fft_tb_arq of fft_tb is

	component fft is
		 port(
			clk: 	in std_logic;
			rst: 	in std_logic;
			ena: 	in std_logic;
			T: 	in std_logic;
			Q: 	out std_logic
		);
	end component;

	signal clk_tb: std_logic := '0';
	signal rst_tb: std_logic := '0';
	signal ena_tb: std_logic := '0';
	signal T_tb: std_logic := '0';
	signal Q_tb: std_logic;
	
begin
	clk_tb <= not clk_tb after 20 ns;
	ena_tb <= '0', '1' after 50 ns;
	T_tb <= '1', '0' after 70 ns,'1' after 100 ns, '0' after 500 ns;
	rst_tb <= '1', '0' after 30 ns;

	DUT:fft
		port map(
			clk => 	clk_tb,
			rst => 	rst_tb,
			ena => 	ena_tb,
			T => 	T_tb,
			Q =>	Q_tb
		);
end;

Codigos/fft/simulacion/fft_tb.vcd
$date
  Fri Apr  2 21:46:17 2021
$end
$version
  GHDL v0
$end
$timescale
  1 fs
$end
$scope module standard $end
$upscope $end
$scope module std_logic_1164 $end
$upscope $end
$scope module fft_tb $end
$var reg 1 ! clk_tb $end
$var reg 1 " rst_tb $end
$var reg 1 # ena_tb $end
$var reg 1 $ t_tb $end
$var reg 1 % q_tb $end
$scope module dut $end
$var reg 1 & clk $end
$var reg 1 ' rst $end
$var reg 1 ( ena $end
$var reg 1 ) t $end
$var reg 1 * q $end
$var reg 1 + q_aux $end
$upscope $end
$upscope $end
$enddefinitions $end
#0
0!
1"
0#
1$
U%
0&
1'
0(
1)
U*
U+
#20000000
1!
1&
U*
#30000000
0"
0'
#40000000
0!
0&
#50000000
1#
1(
#60000000
1!
1&
#70000000
0$
0)
#80000000
0!
0&
#100000000
1!
1$
1&
1)
#120000000
0!
0&
U*
#140000000
1!
1&
#160000000
0!
0&
U*
#180000000
1!
1&
#200000000
0!
0&
U*
#220000000
1!
1&
#240000000
0!
0&
U*
