Codigos/4_mux/fuentes/mux.vhd
library IEEE;
use IEEE.std_logic_1164.all;

entity mux is
	port(
		a_i: 	in std_logic;
		b_i: 	in std_logic;
		sel_i: 	in std_logic;
		sal_o: 	out std_logic
	);
end;

architecture mux_arq of mux is
begin
	sal_o <= (a_i and sel_i) or (b_i and(not(sel_i)));
end;

Codigos/4_mux/fuentes/mux_tb.vhd
library IEEE;
use IEEE.std_logic_1164.all;

entity mux_tb is
end;

architecture mux_tb_arq of mux_tb is

	-- Declaración del componente	
	component mux is
		port(
			a_i: 	in std_logic;
			b_i: 	in std_logic;
			sel_i: 	in std_logic;
			sal_o: 	out std_logic
		);
	end component;

	-- señales de prueba	
	signal a_tb:  std_logic;
	signal b_tb:  std_logic;
	signal sel_tb: std_logic;
	signal sal_tb: std_logic;
	
begin
	sel_tb <= '0', '1' after 30 ns, '0' after 60 ns,'1' after 90 ns, '0' after 120 ns;		
	a_tb <= '1', '0' after 10 ns, '1' after 50 ns;
	b_tb <= '0', '1' after 20 ns, '0' after 70 ns, '1' after 100 ns;

	-- Instancia del componente a probar	
	DUT: mux
		port map(
			a_i => a_tb,
			b_i => b_tb,
			sel_i => sel_tb,
			sal_o => sal_tb
		);

end;

Codigos/4_mux/simulacion/mux_tb.vcd
$date
  Sun Apr  4 10:43:43 2021
$end
$version
  GHDL v0
$end
$timescale
  1 fs
$end
$scope module standard $end
$upscope $end
$scope module std_logic_1164 $end
$upscope $end
$scope module mux_tb $end
$var reg 1 ! a_tb $end
$var reg 1 " b_tb $end
$var reg 1 # sel_tb $end
$var reg 1 $ sal_tb $end
$scope module dut $end
$var reg 1 % a_i $end
$var reg 1 & b_i $end
$var reg 1 ' sel_i $end
$var reg 1 ( sal_o $end
$upscope $end
$upscope $end
$enddefinitions $end
#0
1!
0"
0#
0$
1%
0&
0'
0(
#10000000
0!
0%
#20000000
1"
1$
1&
1(
#30000000
1#
0$
1'
0(
#50000000
1!
1$
1%
1(
#60000000
0#
0'
#70000000
0"
0$
0&
0(
#90000000
1#
1$
1'
1(
#100000000
1"
1&
#120000000
0#
0'
