Codigos/16_contador_BCD_4digitos/fuentes/contador_bcd.vhd
library IEEE;
use IEEE.std_logic_1164.all;
use IEEE.numeric_std.all;

entity contador_bcd is
	generic (
		N: natural := 4
	);
	port(
		clk: 	in std_logic;
		rst: 	in std_logic;
		ena: 	in std_logic;
		cy: 	out std_logic;
		Q: 		out std_logic_vector(N-1 downto 0)
	);
end;

architecture contador_bcd_arq of contador_bcd is

	--Inicializo salidas
	signal Q_aux: std_logic_vector(N-1 downto 0):=std_logic_vector(to_unsigned(0,N));
	
	begin
    proceso_contador: process (ena, clk,rst) is
    	variable count: integer range 0 to 512:=0;
		begin
        if rst = '1' then
            Q_aux <= std_logic_vector(to_unsigned(0,N));
            count:=0;
            cy <='0';
			elsif rising_edge(clk) and ena='1' then
				count:= to_integer(unsigned(Q_aux));
				count:= count+1;
				if count=10 then
				    Q_aux <= std_logic_vector(to_unsigned(0,N));
					count:=0;
					cy <=  '0';
					else
						Q_aux <= std_logic_vector(to_unsigned(count,N));
						if count=9 then
							cy <= '1';
						end if;
				end if;
		end if;
    end process  proceso_contador;
    Q <= Q_aux;
end;

Codigos/16_contador_BCD_4digitos/fuentes/contador_bcd_4d.vhd
library IEEE;
use IEEE.std_logic_1164.all;
use IEEE.numeric_std.all;

entity contador_bcd_4d is
	generic (
		M: natural := 4
	);
	port(
		clk: 	in std_logic;
		rst: 	in std_logic;
		ena: 	in std_logic;
		co: 	out std_logic;
		bcd0,bcd1,bcd2,bcd3: out std_logic_vector(M-1 downto 0)
	);
end;

architecture contador_bcd_4d_arq of contador_bcd_4d is
	component contador_bcd is
		generic (
			N: natural := 4
		);
		port(
			clk: 	in std_logic;
			rst: 	in std_logic;
			ena: 	in std_logic;
			cy: 	out std_logic;
			Q: 		out std_logic_vector(N-1 downto 0)
		);
	end component;

		signal ena_aux: std_logic_vector(M-1 downto 0);
		signal cy_aux: std_logic_vector(M-1 downto 0);
	
	begin
	
	ena_aux(0)<= ena;
	ena_aux(1)<= ena_aux(0) and cy_aux(0);
	ena_aux(2)<= ena_aux(1) and cy_aux(1);
	ena_aux(3)<= ena_aux(2) and cy_aux(2);
	co <= cy_aux(3);
	
		contador_bcd0_inst:contador_bcd
			generic map(N => 4) 
			port map(
				clk =>  clk ,
				rst => 	rst,
				ena => ena_aux(0),
				cy =>  cy_aux(0),
				Q 	=> 	bcd0
			);
			
		contador_bcd1_inst:contador_bcd
			generic map(N => 4) 
			port map(
				clk =>  clk ,
				rst => 	rst,
				ena =>  ena_aux(1),
				cy =>   cy_aux(1),
				Q 	=> 	bcd1
			);
		
		contador_bcd2_inst:contador_bcd
			generic map(N => 4) 
			port map(
				clk =>  clk ,
				rst => 	rst,
				ena =>  ena_aux(2),
				cy =>   cy_aux(2),
				Q 	=> 	bcd2
			);
		
		contador_bcd3_inst:contador_bcd
			generic map(N => 4) 
			port map(
				clk =>  clk ,
				rst => 	rst,
				ena =>  ena_aux(3),
				cy =>   cy_aux(3),
				Q 	=> 	bcd3
			);
end;

Codigos/16_contador_BCD_4digitos/fuentes/contador_bcd_4d_tb.vhd
library IEEE;
use IEEE.std_logic_1164.all;

entity contador_bcd_4d_tb is
		generic (
			M: natural := 4
		);
end;

architecture contador_bcd_4d_tb_arq of contador_bcd_4d_tb is

	component contador_bcd_4d is
		generic (
			M: natural := 4
		);
		port(
			clk: 	in std_logic;
			rst: 	in std_logic;
			ena: 	in std_logic;
			co: 	out std_logic;
			bcd0,bcd1,bcd2,bcd3: out std_logic_vector(M-1 downto 0)
		);
	end component;

	signal clk_tb: std_logic := '0';
	signal rst_tb: std_logic := '0';
	signal ena_tb: std_logic := '0';
	signal cy_tb: std_logic := '0';
	signal bcd0_tb,bcd1_tb,bcd2_tb,bcd3_tb: std_logic_vector(M-1 downto 0);
	
begin
	clk_tb <= not clk_tb after 10 ns;
	ena_tb <= '0', '1' after 50 ns,'0' after 900 ns,'1' after 1 us;
	rst_tb <= '1', '0' after 30 ns, '1' after 600 ns, '0' after 630 ns;

	DUT: contador_bcd_4d
		generic map (M => 4)
		port map(
			clk => 	clk_tb,
			rst => 	rst_tb,
			ena => 	ena_tb,
			co => 	cy_tb,
			bcd0 => 	bcd0_tb,
			bcd1 => 	bcd1_tb,
			bcd2 => 	bcd2_tb,
			bcd3 => 	bcd3_tb
			
		);
end;

Codigos/16_contador_BCD_4digitos/simulacion/contador_bcd_4d_tb.vcd
$date
  Tue Apr  6 15:39:37 2021
$end
$version
  GHDL v0
$end
$timescale
  1 fs
$end
$scope module standard $end
$upscope $end
$scope module std_logic_1164 $end
$upscope $end
$scope module numeric_std $end
$upscope $end
$scope module contador_bcd_4d_tb $end
$var reg 1 ! clk_tb $end
$var reg 1 " rst_tb $end
$var reg 1 # ena_tb $end
$var reg 1 $ cy_tb $end
$var reg 4 % bcd0_tb[3:0] $end
$var reg 4 & bcd1_tb[3:0] $end
$var reg 4 ' bcd2_tb[3:0] $end
$var reg 4 ( bcd3_tb[3:0] $end
$scope module dut $end
$var reg 1 ) clk $end
$var reg 1 * rst $end
$var reg 1 + ena $end
$var reg 1 , co $end
$var reg 4 - bcd0[3:0] $end
$var reg 4 . bcd1[3:0] $end
$var reg 4 / bcd2[3:0] $end
$var reg 4 0 bcd3[3:0] $end
$var reg 4 1 ena_aux[3:0] $end
$var reg 4 2 cy_aux[3:0] $end
$scope module contador_bcd0_inst $end
$var reg 1 3 clk $end
$var reg 1 4 rst $end
$var reg 1 5 ena $end
$var reg 1 6 cy $end
$var reg 4 7 q[3:0] $end
$var reg 4 8 q_aux[3:0] $end
$upscope $end
$scope module contador_bcd1_inst $end
$var reg 1 9 clk $end
$var reg 1 : rst $end
$var reg 1 ; ena $end
$var reg 1 < cy $end
$var reg 4 = q[3:0] $end
$var reg 4 > q_aux[3:0] $end
$upscope $end
$scope module contador_bcd2_inst $end
$var reg 1 ? clk $end
$var reg 1 @ rst $end
$var reg 1 A ena $end
$var reg 1 B cy $end
$var reg 4 C q[3:0] $end
$var reg 4 D q_aux[3:0] $end
$upscope $end
$scope module contador_bcd3_inst $end
$var reg 1 E clk $end
$var reg 1 F rst $end
$var reg 1 G ena $end
$var reg 1 H cy $end
$var reg 4 I q[3:0] $end
$var reg 4 J q_aux[3:0] $end
$upscope $end
$upscope $end
$upscope $end
$enddefinitions $end
#0
0!
1"
0#
0$
b0000 %
b0000 &
b0000 '
b0000 (
0)
1*
0+
0,
b0000 -
b0000 .
b0000 /
b0000 0
b0000 1
b0000 2
03
14
05
06
b0000 7
b0000 8
09
1:
0;
0<
b0000 =
b0000 >
0?
1@
0A
0B
b0000 C
b0000 D
0E
1F
0G
0H
b0000 I
b0000 J
#10000000
1!
1)
13
19
1?
1E
#20000000
0!
0)
03
09
0?
0E
#30000000
1!
0"
1)
0*
13
04
19
0:
1?
0@
1E
0F
#40000000
0!
0)
03
09
0?
0E
#50000000
1!
1#
1)
1+
b0001 1
13
15
19
1?
1E
#60000000
0!
0)
03
09
0?
0E
#70000000
1!
b0001 %
1)
b0001 -
13
b0001 7
b0001 8
19
1?
1E
#80000000
0!
0)
03
09
0?
0E
#90000000
1!
b0010 %
1)
b0010 -
13
b0010 7
b0010 8
19
1?
1E
#100000000
0!
0)
03
09
0?
0E
#110000000
1!
b0011 %
1)
b0011 -
13
b0011 7
b0011 8
19
1?
1E
#120000000
0!
0)
03
09
0?
0E
#130000000
1!
b0100 %
1)
b0100 -
13
b0100 7
b0100 8
19
1?
1E
#140000000
0!
0)
03
09
0?
0E
#150000000
1!
b0101 %
1)
b0101 -
13
b0101 7
b0101 8
19
1?
1E
#160000000
0!
0)
03
09
0?
0E
#170000000
1!
b0110 %
1)
b0110 -
13
b0110 7
b0110 8
19
1?
1E
#180000000
0!
0)
03
09
0?
0E
#190000000
1!
b0111 %
1)
b0111 -
13
b0111 7
b0111 8
19
1?
1E
#200000000
0!
0)
03
09
0?
0E
#210000000
1!
b1000 %
1)
b1000 -
13
b1000 7
b1000 8
19
1?
1E
#220000000
0!
0)
03
09
0?
0E
#230000000
1!
b1001 %
1)
b1001 -
b0011 1
b0001 2
13
16
b1001 7
b1001 8
19
1;
1?
1E
#240000000
0!
0)
03
09
0?
0E
#250000000
1!
b0000 %
b0001 &
1)
b0000 -
b0001 .
b0001 1
b0000 2
13
06
b0000 7
b0000 8
19
0;
b0001 =
b0001 >
1?
1E
#260000000
0!
0)
03
09
0?
0E
#270000000
1!
b0001 %
1)
b0001 -
13
b0001 7
b0001 8
19
1?
1E
#280000000
0!
0)
03
09
0?
0E
#290000000
1!
b0010 %
1)
b0010 -
13
b0010 7
b0010 8
19
1?
1E
#300000000
0!
0)
03
09
0?
0E
#310000000
1!
b0011 %
1)
b0011 -
13
b0011 7
b0011 8
19
1?
1E
#320000000
0!
0)
03
09
0?
0E
#330000000
1!
b0100 %
1)
b0100 -
13
b0100 7
b0100 8
19
1?
1E
#340000000
0!
0)
03
09
0?
0E
#350000000
1!
b0101 %
1)
b0101 -
13
b0101 7
b0101 8
19
1?
1E
#360000000
0!
0)
03
09
0?
0E
#370000000
1!
b0110 %
1)
b0110 -
13
b0110 7
b0110 8
19
1?
1E
#380000000
0!
0)
03
09
0?
0E
#390000000
1!
b0111 %
1)
b0111 -
13
b0111 7
b0111 8
19
1?
1E
#400000000
0!
0)
03
09
0?
0E
#410000000
1!
b1000 %
1)
b1000 -
13
b1000 7
b1000 8
19
1?
1E
#420000000
0!
0)
03
09
0?
0E
#430000000
1!
b1001 %
1)
b1001 -
b0011 1
b0001 2
13
16
b1001 7
b1001 8
19
1;
1?
1E
#440000000
0!
0)
03
09
0?
0E
#450000000
1!
b0000 %
b0010 &
1)
b0000 -
b0010 .
b0001 1
b0000 2
13
06
b0000 7
b0000 8
19
0;
b0010 =
b0010 >
1?
1E
#460000000
0!
0)
03
09
0?
0E
#470000000
1!
b0001 %
1)
b0001 -
13
b0001 7
b0001 8
19
1?
1E
#480000000
0!
0)
03
09
0?
0E
#490000000
1!
b0010 %
1)
b0010 -
13
b0010 7
b0010 8
19
1?
1E
#500000000
0!
0)
03
09
0?
0E
#510000000
1!
b0011 %
1)
b0011 -
13
b0011 7
b0011 8
19
1?
1E
#520000000
0!
0)
03
09
0?
0E
#530000000
1!
b0100 %
1)
b0100 -
13
b0100 7
b0100 8
19
1?
1E
#540000000
0!
0)
03
09
0?
0E
#550000000
1!
b0101 %
1)
b0101 -
13
b0101 7
b0101 8
19
1?
1E
#560000000
0!
0)
03
09
0?
0E
#570000000
1!
b0110 %
1)
b0110 -
13
b0110 7
b0110 8
19
1?
1E
#580000000
0!
0)
03
09
0?
0E
#590000000
1!
b0111 %
1)
b0111 -
13
b0111 7
b0111 8
19
1?
1E
#600000000
0!
1"
b0000 %
b0000 &
0)
1*
b0000 -
b0000 .
03
14
b0000 7
b0000 8
09
1:
b0000 =
b0000 >
0?
1@
0E
1F
#610000000
1!
1)
13
19
1?
1E
#620000000
0!
0)
03
09
0?
0E
#630000000
1!
0"
b0001 %
1)
0*
b0001 -
13
04
b0001 7
b0001 8
19
0:
1?
0@
1E
0F
#640000000
0!
0)
03
09
0?
0E
#650000000
1!
b0010 %
1)
b0010 -
13
b0010 7
b0010 8
19
1?
1E
#660000000
0!
0)
03
09
0?
0E
#670000000
1!
b0011 %
1)
b0011 -
13
b0011 7
b0011 8
19
1?
1E
#680000000
0!
0)
03
09
0?
0E
#690000000
1!
b0100 %
1)
b0100 -
13
b0100 7
b0100 8
19
1?
1E
#700000000
0!
0)
03
09
0?
0E
#710000000
1!
b0101 %
1)
b0101 -
13
b0101 7
b0101 8
19
1?
1E
#720000000
0!
0)
03
09
0?
0E
#730000000
1!
b0110 %
1)
b0110 -
13
b0110 7
b0110 8
19
1?
1E
#740000000
0!
0)
03
09
0?
0E
#750000000
1!
b0111 %
1)
b0111 -
13
b0111 7
b0111 8
19
1?
1E
#760000000
0!
0)
03
09
0?
0E
#770000000
1!
b1000 %
1)
b1000 -
13
b1000 7
b1000 8
19
1?
1E
#780000000
0!
0)
03
09
0?
0E
#790000000
1!
b1001 %
1)
b1001 -
b0011 1
b0001 2
13
16
b1001 7
b1001 8
19
1;
1?
1E
#800000000
0!
0)
03
09
0?
0E
#810000000
1!
b0000 %
b0001 &
1)
b0000 -
b0001 .
b0001 1
b0000 2
13
06
b0000 7
b0000 8
19
0;
b0001 =
b0001 >
1?
1E
#820000000
0!
0)
03
09
0?
0E
#830000000
1!
b0001 %
1)
b0001 -
13
b0001 7
b0001 8
19
1?
1E
#840000000
0!
0)
03
09
0?
0E
#850000000
1!
b0010 %
1)
b0010 -
13
b0010 7
b0010 8
19
1?
1E
#860000000
0!
0)
03
09
0?
0E
#870000000
1!
b0011 %
1)
b0011 -
13
b0011 7
b0011 8
19
1?
1E
#880000000
0!
0)
03
09
0?
0E
#890000000
1!
b0100 %
1)
b0100 -
13
b0100 7
b0100 8
19
1?
1E
#900000000
0!
0#
0)
0+
b0000 1
03
05
09
0?
0E
#910000000
1!
1)
13
19
1?
1E
#920000000
0!
0)
03
09
0?
0E
#930000000
1!
1)
13
19
1?
1E
#940000000
0!
0)
03
09
0?
0E
#950000000
1!
1)
13
19
1?
1E
#960000000
0!
0)
03
09
0?
0E
#970000000
1!
1)
13
19
1?
1E
#980000000
0!
0)
03
09
0?
0E
#990000000
1!
1)
13
19
1?
1E
#1000000000
0!
1#
0)
1+
b0001 1
03
15
09
0?
0E
