Codigos/6_shift_reg/fuentes/ffd.vhd
library IEEE;
use IEEE.std_logic_1164.all;

entity ffd is
	port(
		clk: 	in std_logic;
		rst: 	in std_logic;
		ena: 	in std_logic;
		D: 	in std_logic;
		Q: 	out std_logic
	);
	end ffd;

architecture ffd_arq of ffd is
begin
	process(clk,rst)
		begin
		if rst='1' then
			Q<='0';
		elsif rising_edge(clk) then	
			if ena='1' then	
				Q <= D;	
			end if;
		end if;
	end process;
end ffd_arq;

Codigos/6_shift_reg/fuentes/shift_reg.vhd
library IEEE;
use IEEE.std_logic_1164.all;

entity shift_reg is
	generic (
		N: natural := 4
	);
	port (
		clk: in std_logic;
		rst: in std_logic;
		ena: in std_logic;
		ent: in std_logic;
		sal: out std_logic
	);
end;

architecture shift_reg_arq of shift_reg is
	component ffd is
		port ( 
			rst: 	in std_logic;
			clk: 	in std_logic;
			ena: 	in std_logic;
			D: 	in std_logic;
			Q: 	out std_logic
		);
	end component;
	
	signal D: std_logic_vector(0 to N);
	
begin
	shift_reg_i : for i in 0 to N-1 generate
		ff_inst:ffd
			port map(
				clk =>  clk ,
				ena => ena ,
				D =>   	D(i),
				rst => 	rst,
				Q => 	D(i +1)
			);
	end generate;
D(0) <= ent ;
sal <= D(N) ;
end;

Codigos/6_shift_reg/fuentes/shift_reg_tb.vhd
library IEEE;
use IEEE.std_logic_1164.all;

entity shift_reg_tb is
end;

architecture shift_reg_tb_arq of shift_reg_tb is
	component shift_reg is
		generic (
			N: natural := 4
		);
		port (
			clk: in std_logic;
			rst: in std_logic;
			ena: in std_logic;
			ent: in std_logic;
			sal: out std_logic
		);
	end component;

	signal clk_tb: std_logic := '0';
	signal rst_tb: std_logic := '0';
	signal ena_tb: std_logic := '0';
	signal D_tb: std_logic := '0';
	signal Q_tb: std_logic;
	
begin

	clk_tb <= not clk_tb after 20 ns;
	--clk_tb <= '0', '1' after 20 ns,'0' after 40 ns,'1' after 60 ns,'0' after 80 ns,'1' after 100 ns;
	ena_tb <= '0', '1' after 50 ns;
	D_tb <= '1', '0' after 70 ns;
	rst_tb <= '1', '0' after 30 ns;

	--DUT: entity work.ffd
	--DUT: entity work.shift_reg
	DUT:shift_reg
		port map(
			clk => 	clk_tb,
			rst => 	rst_tb,
			ena => 	ena_tb,
			ent => 	D_tb,
			sal =>	Q_tb
		);
end;

Codigos/6_shift_reg/simulacion/shift_reg_tb.vcd
$date
  Mon Apr  5 03:26:40 2021
$end
$version
  GHDL v0
$end
$timescale
  1 fs
$end
$scope module standard $end
$upscope $end
$scope module std_logic_1164 $end
$upscope $end
$scope module shift_reg_tb $end
$var reg 1 ! clk_tb $end
$var reg 1 " rst_tb $end
$var reg 1 # ena_tb $end
$var reg 1 $ d_tb $end
$var reg 1 % q_tb $end
$scope module dut $end
$var reg 1 & clk $end
$var reg 1 ' rst $end
$var reg 1 ( ena $end
$var reg 1 ) ent $end
$var reg 1 * sal $end
$var reg 5 + d[0:4] $end
$scope module shift_reg_i(0) $end
$scope module ff_inst $end
$var reg 1 , clk $end
$var reg 1 - rst $end
$var reg 1 . ena $end
$var reg 1 / d $end
$var reg 1 0 q $end
$upscope $end
$upscope $end
$scope module shift_reg_i(1) $end
$scope module ff_inst $end
$var reg 1 1 clk $end
$var reg 1 2 rst $end
$var reg 1 3 ena $end
$var reg 1 4 d $end
$var reg 1 5 q $end
$upscope $end
$upscope $end
$scope module shift_reg_i(2) $end
$scope module ff_inst $end
$var reg 1 6 clk $end
$var reg 1 7 rst $end
$var reg 1 8 ena $end
$var reg 1 9 d $end
$var reg 1 : q $end
$upscope $end
$upscope $end
$scope module shift_reg_i(3) $end
$scope module ff_inst $end
$var reg 1 ; clk $end
$var reg 1 < rst $end
$var reg 1 = ena $end
$var reg 1 > d $end
$var reg 1 ? q $end
$upscope $end
$upscope $end
$upscope $end
$upscope $end
$enddefinitions $end
#0
0!
1"
0#
1$
0%
0&
1'
0(
1)
0*
b10000 +
0,
1-
0.
1/
00
01
12
03
04
05
06
17
08
09
0:
0;
1<
0=
0>
0?
#20000000
1!
1&
1,
11
16
1;
#30000000
0"
0'
0-
02
07
0<
#40000000
0!
0&
0,
01
06
0;
#50000000
1#
1(
1.
13
18
1=
#60000000
1!
1&
b11000 +
1,
10
11
14
16
1;
#70000000
0$
0)
b01000 +
0/
#80000000
0!
0&
0,
01
06
0;
#100000000
1!
1&
b00100 +
1,
00
11
04
15
16
19
1;
#120000000
0!
0&
0,
01
06
0;
#140000000
1!
1&
b00010 +
1,
11
05
16
09
1:
1;
1>
#160000000
0!
0&
0,
01
06
0;
#180000000
1!
1%
1&
1*
b00001 +
1,
11
16
0:
1;
0>
1?
#200000000
0!
0&
0,
01
06
0;
#220000000
1!
0%
1&
0*
b00000 +
1,
11
16
1;
0?
