Codigos/17_generador__habiitacion/fuentes/gen_hab.vhd
library IEEE;
use IEEE.std_logic_1164.all;
use IEEE.numeric_std.all;

entity gen_hab is
	generic (
		N: integer := 4
	);
	port(
		clk: 	in std_logic;
		rst: 	in std_logic;
		s: 		out std_logic
	);
end;

architecture gen_hab_arq of gen_hab is

		
	begin
    proceso_gen_Hab: process (clk,rst) is
    	variable count: integer range 0 to 512:=0;
		begin
        if rst = '1' then
            count:=0;
			s <='0';
			elsif rising_edge(clk) then
				count:= count+1;
				s <='0';
				if count=N+1 then
				    count:=0;
					s <= '1';
				end if;
		end if;
    end process  proceso_gen_Hab;
 end;

Codigos/17_generador__habiitacion/fuentes/gen_hab_tb.vhd
library IEEE;
use IEEE.std_logic_1164.all;

entity gen_hab_tb is
end;

architecture contador_bcd_tb_arq of gen_hab_tb is

	component gen_hab is
	generic (
		N: integer := 4
	);
	port(
		clk: 	in std_logic;
		rst: 	in std_logic;
		s: 		out std_logic
	);
	end component;

	signal clk_tb: std_logic := '0';
	signal rst_tb: std_logic := '0';
	signal s_tb: std_logic := '0';

	
begin
	clk_tb <= not clk_tb after 10 ns;
	rst_tb <= '1', '0' after 30 ns, '1' after 400 ns, '0' after 430 ns;

	DUT: gen_hab
		generic map(N => 9)
		port map(
			clk => 	clk_tb,
			rst => 	rst_tb,
			s => 	s_tb
		);
end;

Codigos/17_generador__habiitacion/simulacion/gen_hab_tb.vcd
$date
  Tue Apr  6 17:19:25 2021
$end
$version
  GHDL v0
$end
$timescale
  1 fs
$end
$scope module standard $end
$upscope $end
$scope module std_logic_1164 $end
$upscope $end
$scope module numeric_std $end
$upscope $end
$scope module gen_hab_tb $end
$var reg 1 ! clk_tb $end
$var reg 1 " rst_tb $end
$var reg 1 # s_tb $end
$scope module dut $end
$var reg 1 $ clk $end
$var reg 1 % rst $end
$var reg 1 & s $end
$upscope $end
$upscope $end
$enddefinitions $end
#0
0!
1"
0#
0$
1%
0&
#10000000
1!
1$
#20000000
0!
0$
#30000000
1!
0"
1$
0%
#40000000
0!
0$
#50000000
1!
1$
#60000000
0!
0$
#70000000
1!
1$
#80000000
0!
0$
#90000000
1!
1$
#100000000
0!
0$
#110000000
1!
1$
#120000000
0!
0$
#130000000
1!
1$
#140000000
0!
0$
#150000000
1!
1$
#160000000
0!
0$
#170000000
1!
1$
#180000000
0!
0$
#190000000
1!
1$
#200000000
0!
0$
#210000000
1!
1#
1$
1&
#220000000
0!
0$
#230000000
1!
0#
1$
0&
#240000000
0!
0$
#250000000
1!
1$
#260000000
0!
0$
#270000000
1!
1$
#280000000
0!
0$
#290000000
1!
1$
#300000000
0!
0$
#310000000
1!
1$
#320000000
0!
0$
#330000000
1!
1$
#340000000
0!
0$
#350000000
1!
1$
#360000000
0!
0$
#370000000
1!
1$
#380000000
0!
0$
#390000000
1!
1$
#400000000
0!
1"
0$
1%
#410000000
1!
1$
#420000000
0!
0$
#430000000
1!
0"
1$
0%
#440000000
0!
0$
#450000000
1!
1$
#460000000
0!
0$
#470000000
1!
1$
#480000000
0!
0$
#490000000
1!
1$
#500000000
0!
0$
#510000000
1!
1$
#520000000
0!
0$
#530000000
1!
1$
#540000000
0!
0$
#550000000
1!
1$
#560000000
0!
0$
#570000000
1!
1$
#580000000
0!
0$
#590000000
1!
1$
#600000000
0!
0$
#610000000
1!
1#
1$
1&
#620000000
0!
0$
#630000000
1!
0#
1$
0&
#640000000
0!
0$
#650000000
1!
1$
#660000000
0!
0$
#670000000
1!
1$
#680000000
0!
0$
#690000000
1!
1$
#700000000
0!
0$
#710000000
1!
1$
#720000000
0!
0$
#730000000
1!
1$
#740000000
0!
0$
#750000000
1!
1$
#760000000
0!
0$
#770000000
1!
1$
#780000000
0!
0$
#790000000
1!
1$
#800000000
0!
0$
#810000000
1!
1#
1$
1&
#820000000
0!
0$
#830000000
1!
0#
1$
0&
