Codigos/3_rest1b/fuentes/rest1b.vhd
library IEEE;
use IEEE.std_logic_1164.all;

entity rest1b is
	port(
		a_i: in std_logic;
		b_i: in std_logic;
		c_i: in std_logic;
		r_o: out std_logic;
		c_o: out std_logic
	);
end;

architecture rest1b_arq of rest1b is
begin

	r_o <= a_i xor b_i xor c_i ;
	c_o <= (not(a_i) and b_i) or (not(a_i) and c_i) or (b_i and c_i);
	
end;

Codigos/3_rest1b/fuentes/rest1b_tb.vhd
library IEEE;
use IEEE.std_logic_1164.all;

entity rest1b_tb is
end;

architecture sum1b_tb_arq of rest1b_tb is

	-- Declaracion de componente
	component rest1b is
		port(
			a_i: in std_logic;
			b_i: in std_logic;
			c_i: in std_logic;
			r_o: out std_logic;
			c_o: out std_logic
		);
	end component;
	
	-- Declaracion de senales de prueba
	signal a_tb: std_logic := '0';
	signal b_tb: std_logic := '0';
	signal ci_tb: std_logic := '0';
	signal r_tb: std_logic;
	signal co_tb: std_logic;

begin

	a_tb <= not a_tb after 10 ns;
	b_tb <= not b_tb after 20 ns;
	ci_tb <= not ci_tb after 40 ns;

	DUT: rest1b
		port map(
			a_i	=> a_tb, 
			b_i	=> b_tb,
			c_i 	=> ci_tb,
			r_o	=> r_tb,
			c_o 	=> co_tb
		);
	
end;

Codigos/3_rest1b/simulacion/rest1b_tb.vcd
$date
  Sun Apr  4 21:33:46 2021
$end
$version
  GHDL v0
$end
$timescale
  1 fs
$end
$scope module standard $end
$upscope $end
$scope module std_logic_1164 $end
$upscope $end
$scope module rest1b_tb $end
$var reg 1 ! a_tb $end
$var reg 1 " b_tb $end
$var reg 1 # ci_tb $end
$var reg 1 $ r_tb $end
$var reg 1 % co_tb $end
$scope module dut $end
$var reg 1 & a_i $end
$var reg 1 ' b_i $end
$var reg 1 ( c_i $end
$var reg 1 ) r_o $end
$var reg 1 * c_o $end
$upscope $end
$upscope $end
$enddefinitions $end
#0
0!
0"
0#
0$
0%
0&
0'
0(
0)
0*
#10000000
1!
1$
1&
1)
#20000000
0!
1"
1%
0&
1'
1*
#30000000
1!
0$
0%
1&
0)
0*
#40000000
0!
0"
1#
1$
1%
0&
0'
1(
1)
1*
#50000000
1!
0$
0%
1&
0)
0*
#60000000
0!
1"
1%
0&
1'
1*
#70000000
1!
1$
1&
1)
#80000000
0!
0"
0#
0$
0%
0&
0'
0(
0)
0*
#90000000
1!
1$
1&
1)
#100000000
0!
1"
1%
0&
1'
1*
#110000000
1!
0$
0%
1&
0)
0*
#120000000
0!
0"
1#
1$
1%
0&
0'
1(
1)
1*
#130000000
1!
0$
0%
1&
0)
0*
#140000000
0!
1"
1%
0&
1'
1*
#150000000
1!
1$
1&
1)
#160000000
0!
0"
0#
0$
0%
0&
0'
0(
0)
0*
#170000000
1!
1$
1&
1)
#180000000
0!
1"
1%
0&
1'
1*
#190000000
1!
0$
0%
1&
0)
0*
#200000000
0!
0"
1#
1$
1%
0&
0'
1(
1)
1*
#210000000
1!
0$
0%
1&
0)
0*
#220000000
0!
1"
1%
0&
1'
1*
#230000000
1!
1$
1&
1)
#240000000
0!
0"
0#
0$
0%
0&
0'
0(
0)
0*
#250000000
1!
1$
1&
1)
