Codigos/4_muxN/fuentes/muxN.vhd
library IEEE;
use IEEE.std_logic_1164.all;

entity muxN is
	generic(
		N: integer := 4;  --N:=2**M;
		M: integer := 2
		);
	port(
		ent_i: 	in std_logic_vector(N-1 downto 0);
		sel_i: 	in std_logic_vector(M-1 downto 0);
		sal_o: 	out std_logic
	);
end;

architecture muxN_arq of muxN is
	function word_to_int(word: std_logic_vector) return integer is
		variable result : integer := 0;
	begin
		for index in word'RANGE loop
			if (word(index) = '1') then
			result := result + 2**index;
			end if;
		end loop;
		return result;
	end word_to_int;	

begin
	sal_o <= ent_i(word_to_int(sel_i));
end;

Codigos/4_muxN/fuentes/muxN_tb.vhd
library IEEE;
use IEEE.std_logic_1164.all;

entity muxN_tb is
		generic(
			N: integer := 4;  --N:=2**M;
			M: integer := 2
			);
end;

architecture muxN_tb_arq of muxN_tb is
	-- Declaración del componente	
	component muxN is
		generic(
			N: integer := 4;  --N:=2**M;
			M: integer := 2
			);
		port(
			ent_i: 	in std_logic_vector(N-1 downto 0);
			sel_i: 	in std_logic_vector(M-1 downto 0);
			sal_o: 	out std_logic
		);
	end component;

	-- señales de prueba	
	signal ent_tb:  std_logic_vector(N-1 downto 0);
	signal sel_tb: std_logic_vector(M-1 downto 0);
	signal sal_tb: std_logic;
	
begin
	
	ent_tb(0) <= '1', '0' after 10 ns, '1' after 50 ns;
	ent_tb(1) <= '0', '1' after 20 ns, '0' after 70 ns, '1' after 100 ns;
	ent_tb(2) <= '0', '1' after 125 ns, '0' after 165 ns, '1' after 185 ns;
	ent_tb(3) <= '1', '0' after 20 ns, '1' after 70 ns, '0' after 100 ns;
	sel_tb(0) <= '0','1' after 40 ns, '0' after 80 ns,'1' after 120 ns,
	'0' after 160 ns,'1' after 200 ns;	
	sel_tb(1) <= '0', '1' after 160 ns;	


	-- Instancia del componente a probar	
	DUT: muxN
		port map(
			ent_i => ent_tb,
			sel_i => sel_tb,
			sal_o => sal_tb
		);

end;

Codigos/4_muxN/simulacion/muxN_tb.vcd
$date
  Sun Apr  4 16:12:59 2021
$end
$version
  GHDL v0
$end
$timescale
  1 fs
$end
$scope module standard $end
$upscope $end
$scope module std_logic_1164 $end
$upscope $end
$scope module muxn_tb $end
$var reg 4 ! ent_tb[3:0] $end
$var reg 2 " sel_tb[1:0] $end
$var reg 1 # sal_tb $end
$scope module dut $end
$var reg 4 $ ent_i[3:0] $end
$var reg 2 % sel_i[1:0] $end
$var reg 1 & sal_o $end
$upscope $end
$upscope $end
$enddefinitions $end
#0
b1001 !
b00 "
1#
b1001 $
b00 %
1&
#10000000
b1000 !
0#
b1000 $
0&
#20000000
b0010 !
b0010 $
#40000000
b01 "
1#
b01 %
1&
#50000000
b0011 !
b0011 $
#70000000
b1001 !
0#
b1001 $
0&
#80000000
b00 "
1#
b00 %
1&
#100000000
b0011 !
b0011 $
#120000000
b01 "
b01 %
#125000000
b0111 !
b0111 $
#160000000
b10 "
b10 %
#165000000
b0011 !
0#
b0011 $
0&
#185000000
b0111 !
1#
b0111 $
1&
#200000000
b11 "
0#
b11 %
0&
