Codigos/10_contador_binario_4b/fuentes/ffd.vhd
library IEEE;
use IEEE.std_logic_1164.all;

entity ffd is
	port(
		clk: 	in std_logic;
		rst: 	in std_logic;
		ena: 	in std_logic;
		D: 		in std_logic;
		Q: 		out std_logic
	);
	end ffd;

architecture ffd_arq of ffd is
begin
	process(clk)
		begin
		if rising_edge(clk) then
			if rst = '1' then
				Q <= '0';
			elsif ena = '1' then
				Q <= D;
			end if;			
		end if;	


	end process;
end ffd_arq;

Codigos/10_contador_binario_4b/fuentes/contador_bcd.vhd
library IEEE;
use IEEE.std_logic_1164.all;

entity contador_bcd is
	generic (
		N: natural := 4
	);
	port(
		clk: 	in std_logic;
		rst: 	in std_logic;
		ena: 	in std_logic;
		Q: 		out std_logic_vector(N-1 downto 0)
	);
	end contador_bcd;

architecture contador_bcd_arq of contador_bcd is
	component ffd is
		port(
			clk: 	in std_logic;
			rst: 	in std_logic;
			ena: 	in std_logic;
			D: 		in std_logic;
			Q: 		out std_logic
		);
	end component;
	
	signal D: std_logic_vector(N-1 downto 0);
	signal ena_aux: std_logic_vector(N downto 0);
	signal Q_aux: std_logic_vector(N downto 0);
	
	begin
		Q <= Q_aux(N downto 1);
		Q_aux(0)<='1';
		D(0)<= Q_aux(1) xor '1';
		D(1)<= Q_aux(2) xor Q_aux(1);
		D(2)<= Q_aux(3) xor (Q_aux(1) and Q_aux(2));
		D(3)<= Q_aux(4) xor (Q_aux(1) and Q_aux(2) and Q_aux(3));

		ffd_i : for i in 0 to N-1 generate
			ff_inst:ffd
				port map(
					clk =>	clk ,
					D 	=> 	D(i),
					ena =>	ena,
					rst =>	rst,
					Q 	=>	Q_aux(i+1)
				);
		end generate ffd_i;
end ;

Codigos/10_contador_binario_4b/fuentes/contador_bcd_tb.vhd
library IEEE;
use IEEE.std_logic_1164.all;

entity contador_bcd_tb is

end;

architecture contador_bcd_tb_arq of contador_bcd_tb is

	component contador_bcd is
		generic (
			N: natural := 4
		);
		port(
			clk: 	in std_logic;
			rst: 	in std_logic;
			ena: 	in std_logic;
			Q: 		out std_logic_vector(N-1 downto 0)
		);
	end component;

	signal clk_tb: std_logic := '0';
	signal rst_tb: std_logic := '0';
	signal ena_tb: std_logic := '0';
	signal Q_tb: std_logic_vector(N-1 downto 0);
	
begin
	clk_tb <= not clk_tb after 10 ns;
	ena_tb <= '0', '1' after 50 ns, '0' after 300 ns, '1' after 330 ns;
	rst_tb <= '1', '0' after 40 ns, '1' after 400 ns, '0' after 430 ns;

	DUT: contador_bcd
		generic map (N=>4)
		port map(
			clk => 	clk_tb,
			rst => 	rst_tb,
			ena => 	ena_tb,
			Q =>	Q_tb
		);
end;

Codigos/10_contador_binario_4b/simulacion/contador_bcd_tb.vcd
$date
  Tue Apr  6 22:10:43 2021
$end
$version
  GHDL v0
$end
$timescale
  1 fs
$end
$scope module standard $end
$upscope $end
$scope module std_logic_1164 $end
$upscope $end
$scope module contador_bcd_tb $end
$var reg 1 ! clk_tb $end
$var reg 1 " rst_tb $end
$var reg 1 # ena_tb $end
$var reg 4 $ q_tb[3:0] $end
$scope module dut $end
$var reg 1 % clk $end
$var reg 1 & rst $end
$var reg 1 ' ena $end
$var reg 4 ( q[3:0] $end
$var reg 4 ) d[3:0] $end
$var reg 5 * ena_aux[4:0] $end
$var reg 5 + q_aux[4:0] $end
$scope module ffd_i(0) $end
$scope module ff_inst $end
$var reg 1 , clk $end
$var reg 1 - rst $end
$var reg 1 . ena $end
$var reg 1 / d $end
$var reg 1 0 q $end
$upscope $end
$upscope $end
$scope module ffd_i(1) $end
$scope module ff_inst $end
$var reg 1 1 clk $end
$var reg 1 2 rst $end
$var reg 1 3 ena $end
$var reg 1 4 d $end
$var reg 1 5 q $end
$upscope $end
$upscope $end
$scope module ffd_i(2) $end
$scope module ff_inst $end
$var reg 1 6 clk $end
$var reg 1 7 rst $end
$var reg 1 8 ena $end
$var reg 1 9 d $end
$var reg 1 : q $end
$upscope $end
$upscope $end
$scope module ffd_i(3) $end
$scope module ff_inst $end
$var reg 1 ; clk $end
$var reg 1 < rst $end
$var reg 1 = ena $end
$var reg 1 > d $end
$var reg 1 ? q $end
$upscope $end
$upscope $end
$upscope $end
$upscope $end
$enddefinitions $end
#0
0!
1"
0#
bUUUU $
0%
1&
0'
bUUUU (
bUUUU )
bUUUUU *
bUUUU1 +
0,
1-
0.
U/
U0
01
12
03
U4
U5
06
17
08
U9
U:
0;
1<
0=
U>
U?
#10000000
1!
b0000 $
1%
b0000 (
b0001 )
b00001 +
1,
1/
00
11
04
05
16
09
0:
1;
0>
0?
#20000000
0!
0%
0,
01
06
0;
#30000000
1!
1%
1,
11
16
1;
#40000000
0!
0"
0%
0&
0,
0-
01
02
06
07
0;
0<
#50000000
1!
1#
b0001 $
1%
1'
b0001 (
b0010 )
b00011 +
1,
1.
0/
10
11
13
14
16
18
1;
1=
#60000000
0!
0%
0,
01
06
0;
#70000000
1!
b0010 $
1%
b0010 (
b0011 )
b00101 +
1,
1/
00
11
15
16
1;
#80000000
0!
0%
0,
01
06
0;
#90000000
1!
b0011 $
1%
b0011 (
b0100 )
b00111 +
1,
0/
10
11
04
16
19
1;
#100000000
0!
0%
0,
01
06
0;
#110000000
1!
b0100 $
1%
b0100 (
b0101 )
b01001 +
1,
1/
00
11
05
16
1:
1;
#120000000
0!
0%
0,
01
06
0;
#130000000
1!
b0101 $
1%
b0101 (
b0110 )
b01011 +
1,
0/
10
11
14
16
1;
#140000000
0!
0%
0,
01
06
0;
#150000000
1!
b0110 $
1%
b0110 (
b0111 )
b01101 +
1,
1/
00
11
15
16
1;
#160000000
0!
0%
0,
01
06
0;
#170000000
1!
b0111 $
1%
b0111 (
b1000 )
b01111 +
1,
0/
10
11
04
16
09
1;
1>
#180000000
0!
0%
0,
01
06
0;
#190000000
1!
b1000 $
1%
b1000 (
b1001 )
b10001 +
1,
1/
00
11
05
16
0:
1;
1?
#200000000
0!
0%
0,
01
06
0;
#210000000
1!
b1001 $
1%
b1001 (
b1010 )
b10011 +
1,
0/
10
11
14
16
1;
#220000000
0!
0%
0,
01
06
0;
#230000000
1!
b1010 $
1%
b1010 (
b1011 )
b10101 +
1,
1/
00
11
15
16
1;
#240000000
0!
0%
0,
01
06
0;
#250000000
1!
b1011 $
1%
b1011 (
b1100 )
b10111 +
1,
0/
10
11
04
16
19
1;
#260000000
0!
0%
0,
01
06
0;
#270000000
1!
b1100 $
1%
b1100 (
b1101 )
b11001 +
1,
1/
00
11
05
16
1:
1;
#280000000
0!
0%
0,
01
06
0;
#290000000
1!
b1101 $
1%
b1101 (
b1110 )
b11011 +
1,
0/
10
11
14
16
1;
#300000000
0!
0#
0%
0'
0,
0.
01
03
06
08
0;
0=
#310000000
1!
1%
1,
11
16
1;
#320000000
0!
0%
0,
01
06
0;
#330000000
1!
1#
b1110 $
1%
1'
b1110 (
b1111 )
b11101 +
1,
1.
1/
00
11
13
15
16
18
1;
1=
#340000000
0!
0%
0,
01
06
0;
#350000000
1!
b1111 $
1%
b1111 (
b0000 )
b11111 +
1,
0/
10
11
04
16
09
1;
0>
#360000000
0!
0%
0,
01
06
0;
#370000000
1!
b0000 $
1%
b0000 (
b0001 )
b00001 +
1,
1/
00
11
05
16
0:
1;
0?
#380000000
0!
0%
0,
01
06
0;
#390000000
1!
b0001 $
1%
b0001 (
b0010 )
b00011 +
1,
0/
10
11
14
16
1;
#400000000
0!
1"
0%
1&
0,
1-
01
12
06
17
0;
1<
#410000000
1!
b0000 $
1%
b0000 (
b0001 )
b00001 +
1,
1/
00
11
04
16
1;
#420000000
0!
0%
0,
01
06
0;
#430000000
1!
0"
b0001 $
1%
0&
b0001 (
b0010 )
b00011 +
1,
0-
0/
10
11
02
14
16
07
1;
0<
#440000000
0!
0%
0,
01
06
0;
#450000000
1!
b0010 $
1%
b0010 (
b0011 )
b00101 +
1,
1/
00
11
15
16
1;
#460000000
0!
0%
0,
01
06
0;
#470000000
1!
b0011 $
1%
b0011 (
b0100 )
b00111 +
1,
0/
10
11
04
16
19
1;
#480000000
0!
0%
0,
01
06
0;
#490000000
1!
b0100 $
1%
b0100 (
b0101 )
b01001 +
1,
1/
00
11
05
16
1:
1;
