Codigos/10_contador_binario_4b/fuentes/ffd.vhd
-- Es un FF D que no tiene habilitación
library IEEE;
use IEEE.std_logic_1164.all;

entity ffd is
	port(
		clk: 	in std_logic;
		rst: 	in std_logic;
		D: 		in std_logic;
		Q: 		out std_logic
	);
	end ffd;

architecture ffd_arq of ffd is
begin
	process(clk,rst)
		begin
		if rst='1' then
			Q<='0';
		elsif rising_edge(clk) then	
				Q <= D;	
		end if;
	end process;
end ffd_arq;

Codigos/10_contador_binario_4b/fuentes/contador_bcd.vhd
library IEEE;
use IEEE.std_logic_1164.all;

entity contador_bcd is
	generic (
		N: natural := 4
	);
	port(
		clk: 	in std_logic;
		rst: 	in std_logic;
		ena: 	in std_logic;
		Q: 		out std_logic_vector(N-1 downto 0)
	);
	end contador_bcd;

architecture contador_bcd_arq of contador_bcd is
	component ffd is
		 port(
			clk: 	in std_logic;
			rst: 	in std_logic;
			D: 		in std_logic;
			Q: 		out std_logic
		);
	end component;
	
	signal D: std_logic_vector(N-1 downto 0);
	signal ena_aux: std_logic_vector(N downto 0);
	signal Q_aux: std_logic_vector(N downto 0);
	
	--constant pepe: integer:=4;
	
	begin
	process (clk,ena) is
	begin
	Q_aux(0)<='1';
	ena_aux(0) <= ena;
	--N=1
	D(0)<= Q_aux(1) xor ena_aux(0);
	ena_aux(1)<=Q_aux(0) and ena_aux(0);
	--N=2
	D(1)<= Q_aux(2) xor ena_aux(1);
	ena_aux(2)<=Q_aux(1) and ena_aux(1);
	--N=3
	D(2)<= Q_aux(3) xor ena_aux(2);
	ena_aux(3)<=Q_aux(2) and ena_aux(2);
	--N=4
	D(3)<= Q_aux(4) xor ena_aux(3);
	ena_aux(4)<=Q_aux(3) and ena_aux(3);
		
	Q <= Q_aux(N downto 1);
	end process;
	
	--	process (ena) is
	--		begin
	--			Q_aux(0)<='1';
	--			ena_aux(0) <= ena ;
	--			if ena='1'then
	--				for j in 1 to N loop
	--					D(j-1)<= Q_aux(j) xor ena_aux(j-1);
	--					ena_aux(j)<=Q_aux(j-1) and ena_aux(j-1);
	--				end loop;
	--			Q(2) <= ena;
	--			end if;	
	--		--Q <= Q_aux(N downto 1);	
	--		Q(0) <= Q_aux(1);
	--		Q(1) <= '1';
	--		Q(3) <= Q_aux(4);
				
	--	end process;
	
	
		ffd_i : for i in 0 to N-1 generate
			ff_inst:ffd
				port map(
					clk =>  clk ,
					D 	=> 	D(i),
					rst => 	rst,
					Q 	=> 	Q_aux(i+1)
				);
		end generate ffd_i;
end ;

Codigos/10_contador_binario_4b/fuentes/contador_bcd_tb.vhd
library IEEE;
use IEEE.std_logic_1164.all;

entity contador_bcd_tb is
		generic (
			N: natural := 4
		);
end;

architecture contador_bcd_tb_arq of contador_bcd_tb is

	component contador_bcd is
		generic (
			N: natural := 4
		);
		port(
			clk: 	in std_logic;
			rst: 	in std_logic;
			ena: 	in std_logic;
			Q: 		out std_logic_vector(N-1 downto 0)
		);
	end component;

	signal clk_tb: std_logic := '0';
	signal rst_tb: std_logic := '0';
	signal ena_tb: std_logic := '0';
	signal Q_tb: std_logic_vector(N-1 downto 0);
	
begin
	clk_tb <= not clk_tb after 20 ns;
	--clk_tb <= '0','1' after 20 ns, '0' after 40 ns, '1' after 60 ns, '0' after 80 ns, '1' after 100 ns,'0' after 120 ns;
	ena_tb <= '0', '1' after 50 ns;
	rst_tb <= '1', '0' after 40 ns, '1' after 400 ns, '0' after 430 ns;

	DUT: contador_bcd
		port map(
			clk => 	clk_tb,
			rst => 	rst_tb,
			ena => 	ena_tb,
			Q =>	Q_tb
		);
end;

Codigos/10_contador_binario_4b/simulacion/contador_bcd_tb.vcd
$date
  Tue Apr  6 09:03:27 2021
$end
$version
  GHDL v0
$end
$timescale
  1 fs
$end
$scope module standard $end
$upscope $end
$scope module std_logic_1164 $end
$upscope $end
$scope module contador_bcd_tb $end
$var reg 1 ! clk_tb $end
$var reg 1 " rst_tb $end
$var reg 1 # ena_tb $end
$var reg 4 $ q_tb[3:0] $end
$scope module dut $end
$var reg 1 % clk $end
$var reg 1 & rst $end
$var reg 1 ' ena $end
$var reg 4 ( q[3:0] $end
$var reg 4 ) d[3:0] $end
$var reg 5 * ena_aux[4:0] $end
$var reg 5 + q_aux[4:0] $end
$scope module ffd_i(0) $end
$scope module ff_inst $end
$var reg 1 , clk $end
$var reg 1 - rst $end
$var reg 1 . d $end
$var reg 1 / q $end
$upscope $end
$upscope $end
$scope module ffd_i(1) $end
$scope module ff_inst $end
$var reg 1 0 clk $end
$var reg 1 1 rst $end
$var reg 1 2 d $end
$var reg 1 3 q $end
$upscope $end
$upscope $end
$scope module ffd_i(2) $end
$scope module ff_inst $end
$var reg 1 4 clk $end
$var reg 1 5 rst $end
$var reg 1 6 d $end
$var reg 1 7 q $end
$upscope $end
$upscope $end
$scope module ffd_i(3) $end
$scope module ff_inst $end
$var reg 1 8 clk $end
$var reg 1 9 rst $end
$var reg 1 : d $end
$var reg 1 ; q $end
$upscope $end
$upscope $end
$upscope $end
$upscope $end
$enddefinitions $end
#0
0!
1"
0#
bUUUU $
0%
1&
0'
bUUUU (
bUUUU )
bUUUU0 *
b00001 +
0,
1-
U.
0/
00
11
U2
03
04
15
U6
07
08
19
U:
0;
#20000000
1!
b0000 $
1%
b0000 (
bUUU0 )
b00000 *
1,
0.
10
14
18
#40000000
0!
0"
0%
0&
b0000 )
0,
0-
00
01
02
04
05
06
08
09
0:
#50000000
1#
1'
b00001 *
#60000000
1!
1%
b0001 )
b00011 *
1,
1.
10
14
18
#80000000
0!
0%
b0011 )
0,
00
12
04
08
#100000000
1!
1%
b00111 +
1,
1/
10
13
14
18
#120000000
0!
b0011 $
0%
b0011 (
b0000 )
b00111 *
0,
0.
00
02
04
08
#140000000
1!
1%
b0100 )
b01111 *
b00001 +
1,
0/
10
03
14
16
18
#160000000
0!
b0000 $
0%
b0000 (
b1111 )
b00011 *
0,
1.
00
12
04
08
1:
#180000000
1!
1%
b0011 )
b11111 +
1,
1/
10
13
14
06
17
18
0:
1;
#200000000
0!
b1111 $
0%
b1111 (
b1100 )
b00111 *
0,
0.
00
02
04
16
08
1:
#220000000
1!
1%
b1000 )
b01111 *
b11001 +
1,
0/
10
03
14
06
18
#240000000
0!
b1100 $
0%
b1100 (
b0011 )
b10011 *
0,
1.
00
12
04
08
0:
#260000000
1!
1%
b1111 )
b00011 *
b00111 +
1,
1/
10
13
14
16
07
18
1:
0;
#280000000
0!
b0011 $
0%
b0011 (
b0000 )
b00111 *
0,
0.
00
02
04
06
08
0:
#300000000
1!
1%
b0100 )
b01111 *
b00001 +
1,
0/
10
03
14
16
18
#320000000
0!
b0000 $
0%
b0000 (
b1111 )
b00011 *
0,
1.
00
12
04
08
1:
#340000000
1!
1%
b0011 )
b11111 +
1,
1/
10
13
14
06
17
18
0:
1;
#360000000
0!
b1111 $
0%
b1111 (
b1100 )
b00111 *
0,
0.
00
02
04
16
08
1:
#380000000
1!
1%
b1000 )
b01111 *
b11001 +
1,
0/
10
03
14
06
18
#400000000
0!
1"
b1100 $
0%
1&
b1100 (
b0011 )
b10011 *
b00001 +
0,
1-
1.
00
11
12
04
15
07
08
19
0:
0;
#420000000
1!
b0000 $
1%
b0000 (
b00011 *
1,
10
14
18
#430000000
0"
0&
0-
01
05
09
#440000000
0!
0%
0,
00
04
08
#460000000
1!
1%
b00111 +
1,
1/
10
13
14
18
#480000000
0!
b0011 $
0%
b0011 (
b0000 )
b00111 *
0,
0.
00
02
04
08
#500000000
1!
1%
b0100 )
b01111 *
b00001 +
1,
0/
10
03
14
16
18
