Codigos/13_contador_binario_Nb/fuentes/contador_bcd.vhd
library IEEE;
use IEEE.std_logic_1164.all;
use IEEE.numeric_std.all;

entity contador_bcd is
	generic (
		N: natural := 6
	);
	port(
		clk: 	in std_logic;
		rst: 	in std_logic;
		ena: 	in std_logic;
		Q: 		out std_logic_vector(N-1 downto 0)
	);
end;

architecture contador_bcd_arq of contador_bcd is

	--Inicializo salidas
	signal Q_aux: std_logic_vector(N-1 downto 0):=std_logic_vector(to_unsigned(0,N));
	
	begin
    proceso_contador: process (ena, clk,rst) is
    	variable count: integer range 0 to 512:=0;
		begin
        if rst = '1' then
            Q_aux <= std_logic_vector(to_unsigned(0,N));
            count:=0;
			elsif rising_edge(clk) and ena='1' then
				count:= to_integer(unsigned(Q_aux));
				count:= count+1;
				Q_aux <= std_logic_vector(to_unsigned(count,N));
		end if;
    end process  proceso_contador;
    Q <= Q_aux;
end;

Codigos/13_contador_binario_Nb/fuentes/contador_bcd_tb.vhd
library IEEE;
use IEEE.std_logic_1164.all;

entity contador_bcd_tb is
		generic (
			N: natural := 6
		);
end;

architecture contador_bcd_tb_arq of contador_bcd_tb is

	component contador_bcd is
		generic (
			N: natural := 6
		);
		port(
			clk: 	in std_logic;
			rst: 	in std_logic;
			ena: 	in std_logic;
			Q: 		out std_logic_vector(N-1 downto 0)
		);
	end component;

	signal clk_tb: std_logic := '0';
	signal rst_tb: std_logic := '0';
	signal ena_tb: std_logic := '0';
	signal Q_tb: std_logic_vector(N-1 downto 0);
	
begin
	clk_tb <= not clk_tb after 10 ns;
	ena_tb <= '0', '1' after 50 ns,'0' after 600 ns,'1' after 750 ns;
	rst_tb <= '1', '0' after 30 ns, '1' after 400 ns, '0' after 430 ns;

	DUT: contador_bcd
		port map(
			clk => 	clk_tb,
			rst => 	rst_tb,
			ena => 	ena_tb,
			Q =>	Q_tb
		);
end;

Codigos/13_contador_binario_Nb/simulacion/contador_bcd_tb.vcd
$date
  Tue Apr  6 11:05:24 2021
$end
$version
  GHDL v0
$end
$timescale
  1 fs
$end
$scope module standard $end
$upscope $end
$scope module std_logic_1164 $end
$upscope $end
$scope module numeric_std $end
$upscope $end
$scope module contador_bcd_tb $end
$var reg 1 ! clk_tb $end
$var reg 1 " rst_tb $end
$var reg 1 # ena_tb $end
$var reg 6 $ q_tb[5:0] $end
$scope module dut $end
$var reg 1 % clk $end
$var reg 1 & rst $end
$var reg 1 ' ena $end
$var reg 6 ( q[5:0] $end
$var reg 6 ) q_aux[5:0] $end
$upscope $end
$upscope $end
$enddefinitions $end
#0
0!
1"
0#
b000000 $
0%
1&
0'
b000000 (
b000000 )
#10000000
1!
1%
#20000000
0!
0%
#30000000
1!
0"
1%
0&
#40000000
0!
0%
#50000000
1!
1#
b000001 $
1%
1'
b000001 (
b000001 )
#60000000
0!
0%
#70000000
1!
b000010 $
1%
b000010 (
b000010 )
#80000000
0!
0%
#90000000
1!
b000011 $
1%
b000011 (
b000011 )
#100000000
0!
0%
#110000000
1!
b000100 $
1%
b000100 (
b000100 )
#120000000
0!
0%
#130000000
1!
b000101 $
1%
b000101 (
b000101 )
#140000000
0!
0%
#150000000
1!
b000110 $
1%
b000110 (
b000110 )
#160000000
0!
0%
#170000000
1!
b000111 $
1%
b000111 (
b000111 )
#180000000
0!
0%
#190000000
1!
b001000 $
1%
b001000 (
b001000 )
#200000000
0!
0%
#210000000
1!
b001001 $
1%
b001001 (
b001001 )
#220000000
0!
0%
#230000000
1!
b001010 $
1%
b001010 (
b001010 )
#240000000
0!
0%
#250000000
1!
b001011 $
1%
b001011 (
b001011 )
#260000000
0!
0%
#270000000
1!
b001100 $
1%
b001100 (
b001100 )
#280000000
0!
0%
#290000000
1!
b001101 $
1%
b001101 (
b001101 )
#300000000
0!
0%
#310000000
1!
b001110 $
1%
b001110 (
b001110 )
#320000000
0!
0%
#330000000
1!
b001111 $
1%
b001111 (
b001111 )
#340000000
0!
0%
#350000000
1!
b010000 $
1%
b010000 (
b010000 )
#360000000
0!
0%
#370000000
1!
b010001 $
1%
b010001 (
b010001 )
#380000000
0!
0%
#390000000
1!
b010010 $
1%
b010010 (
b010010 )
#400000000
0!
1"
b000000 $
0%
1&
b000000 (
b000000 )
#410000000
1!
1%
#420000000
0!
0%
#430000000
1!
0"
b000001 $
1%
0&
b000001 (
b000001 )
#440000000
0!
0%
#450000000
1!
b000010 $
1%
b000010 (
b000010 )
#460000000
0!
0%
#470000000
1!
b000011 $
1%
b000011 (
b000011 )
#480000000
0!
0%
#490000000
1!
b000100 $
1%
b000100 (
b000100 )
#500000000
0!
0%
#510000000
1!
b000101 $
1%
b000101 (
b000101 )
#520000000
0!
0%
#530000000
1!
b000110 $
1%
b000110 (
b000110 )
#540000000
0!
0%
#550000000
1!
b000111 $
1%
b000111 (
b000111 )
#560000000
0!
0%
#570000000
1!
b001000 $
1%
b001000 (
b001000 )
#580000000
0!
0%
#590000000
1!
b001001 $
1%
b001001 (
b001001 )
#600000000
0!
0#
0%
0'
#610000000
1!
1%
#620000000
0!
0%
#630000000
1!
1%
#640000000
0!
0%
#650000000
1!
1%
#660000000
0!
0%
#670000000
1!
1%
#680000000
0!
0%
#690000000
1!
1%
#700000000
0!
0%
#710000000
1!
1%
#720000000
0!
0%
#730000000
1!
1%
#740000000
0!
0%
#750000000
1!
1#
b001010 $
1%
1'
b001010 (
b001010 )
#760000000
0!
0%
#770000000
1!
b001011 $
1%
b001011 (
b001011 )
#780000000
0!
0%
#790000000
1!
b001100 $
1%
b001100 (
b001100 )
#800000000
0!
0%
#810000000
1!
b001101 $
1%
b001101 (
b001101 )
#820000000
0!
0%
#830000000
1!
b001110 $
1%
b001110 (
b001110 )
#840000000
0!
0%
#850000000
1!
b001111 $
1%
b001111 (
b001111 )
#860000000
0!
0%
#870000000
1!
b010000 $
1%
b010000 (
b010000 )
#880000000
0!
0%
#890000000
1!
b010001 $
1%
b010001 (
b010001 )
#900000000
0!
0%
#910000000
1!
b010010 $
1%
b010010 (
b010010 )
#920000000
0!
0%
#930000000
1!
b010011 $
1%
b010011 (
b010011 )
#940000000
0!
0%
#950000000
1!
b010100 $
1%
b010100 (
b010100 )
#960000000
0!
0%
#970000000
1!
b010101 $
1%
b010101 (
b010101 )
#980000000
0!
0%
#990000000
1!
b010110 $
1%
b010110 (
b010110 )
